RP1210/Commands.py
RP1210/J1939.py
RP1210/RP1210.py
RP1210/__init__.py
RP1210/UDS/Authentication.py
RP1210/UDS/ClearDiagnosticInformation.py
RP1210/UDS/CommunicationControl.py
RP1210/UDS/ControlDTCSetting.py
RP1210/UDS/DiagnosticSessionControl.py
RP1210/UDS/DynamicallyDefineDataIdentifier.py
RP1210/UDS/ECUReset.py
RP1210/UDS/InputOutputControlByIdentifier.py
RP1210/UDS/LinkControl.py
RP1210/UDS/ReadDTCInformation.py
RP1210/UDS/ReadDataByIdentifier.py
RP1210/UDS/ReadDataByPeriodicIdentifier.py
RP1210/UDS/ReadMemoryByAddress.py
RP1210/UDS/ReadScalingDataByIdentifier.py
RP1210/UDS/RequestDownload.py
RP1210/UDS/RequestFileTransfer.py
RP1210/UDS/RequestTransferExit.py
RP1210/UDS/RequestUpload.py
RP1210/UDS/ResponseOnEvent.py
RP1210/UDS/RoutineControl.py
RP1210/UDS/SecuredDataTransmission.py
RP1210/UDS/SecurityAccess.py
RP1210/UDS/TesterPresent.py
RP1210/UDS/TransferData.py
RP1210/UDS/UDS.py
RP1210/UDS/WriteDataByIdentifier.py
RP1210/UDS/WriteMemoryByAddress.py
RP1210/UDS/__init__.py
RP1210-0.0.26.dist-info/LICENSE
RP1210-0.0.26.dist-info/METADATA
RP1210-0.0.26.dist-info/WHEEL
RP1210-0.0.26.dist-info/top_level.txt
RP1210-0.0.26.dist-info/RECORD
