Metadata-Version: 2.1
Name: RP1210
Version: 0.0.26
Summary: A Python32 implementation of the RP1210C standard.
Home-page: https://github.com/dfieschko/RP1210
Author: Darius Fieschko
Author-email: dfieschko@gmail.com
License: MIT
Project-URL: Wiki, https://github.com/dfieschko/RP1210/wiki
Project-URL: Issues, https://github.com/dfieschko/RP1210/issues
Project-URL: Discussions, https://github.com/dfieschko/RP1210/discussions
Keywords: RP1210,RP1210C,J1939,CAN,UDS
Classifier: Development Status :: 3 - Alpha
Classifier: Intended Audience :: Developers
Classifier: Topic :: Software Development :: Libraries :: Python Modules
Classifier: License :: OSI Approved :: MIT License
Classifier: Programming Language :: Python :: 3
Classifier: Programming Language :: Python :: 3.9
Classifier: Programming Language :: Python :: 3.10
Classifier: Programming Language :: Python :: 3.11
Classifier: Operating System :: Microsoft :: Windows
Requires-Python: >=3.9
License-File: LICENSE
